[{"bank_name":"الأهلي المصري (NBE)","buy_price":"71.31","sell_price":"71.99","last_update":""},{"bank_name":"كريدي أجريكول (CA)","buy_price":"71.22","sell_price":"71.90","last_update":""},{"bank_name":"أبوظبي التجاري (ADCB)","buy_price":"71.22","sell_price":"71.90","last_update":""},{"bank_name":"أبوظبي الإسلامي (ADIB)","buy_price":"71.22","sell_price":"71.90","last_update":""},{"bank_name":"الأهلي الكويتي (ABK)","buy_price":"71.03","sell_price":"71.89","last_update":""},{"bank_name":"البركة (Al Baraka)","buy_price":"71.22","sell_price":"71.90","last_update":""},{"bank_name":"المصرف العربي (AIB)","buy_price":"71.28","sell_price":"71.97","last_update":""},{"bank_name":"التجاري الدولي (CIB)","buy_price":"71.22","sell_price":"71.90","last_update":""},{"bank_name":"بنك نكست (NXT)","buy_price":"71.28","sell_price":"71.97","last_update":""},{"bank_name":"بنك مصر (BM)","buy_price":"71.58","sell_price":"71.89","last_update":""},{"bank_name":"بنك الإسكندرية (ALEXBANK)","buy_price":"71.17","sell_price":"71.86","last_update":""},{"bank_name":"المصري الخليجي (EG Bank)","buy_price":"71.26","sell_price":"72.01","last_update":""},{"bank_name":"الإمارات دبي (Emirates NBD)","buy_price":"71.17","sell_price":"71.86","last_update":""},{"bank_name":"بنك فيصل (Faisal)","buy_price":"71.21","sell_price":"71.89","last_update":""},{"bank_name":"التعمير والإسكان (HDB)","buy_price":"71.28","sell_price":"71.97","last_update":""},{"bank_name":"التنمية الصناعية (IDB)","buy_price":"71.31","sell_price":"71.99","last_update":""},{"bank_name":"ميد بنك (MID Bank)","buy_price":"71.51","sell_price":"72.06","last_update":""},{"bank_name":"الكويت الوطني (NBK)","buy_price":"71.22","sell_price":"71.90","last_update":""},{"bank_name":"بنك الشركة المصرفية (SAIB)","buy_price":"71.34","sell_price":"72.02","last_update":""},{"bank_name":"قناة السويس (SCB)","buy_price":"71.31","sell_price":"71.99","last_update":""},{"bank_name":"المصرف المتحد (UB)","buy_price":"70.95","sell_price":"71.95","last_update":""},{"bank_name":"اتش اس بي سي (HSBC)","buy_price":"71.28","sell_price":"71.97","last_update":""},{"bank_name":"بنك بيت التمويل الكويتي (KFH)","buy_price":"71.28","sell_price":"71.97","last_update":""},{"bank_name":"العقاري المصري العربي (EALB)","buy_price":"71.28","sell_price":"71.97","last_update":""},{"bank_name":"العربي الأفريقي (AAIB)","buy_price":"71.31","sell_price":"71.99","last_update":""},{"bank_name":"أبوظبي اﻷول (FABMISR)","buy_price":"71.56","sell_price":"71.78","last_update":""}]