[{"item_name":"1 Gold PoundE","buy_price":"56656.0","sell_price":"55619.0","last_update":"١٧‏/٤‏/٢٠٢٦، ١١:٣٠:١٠ ص"},{"item_name":"21K/E","buy_price":"7033.4","sell_price":"6932.9","last_update":"١٧‏/٤‏/٢٠٢٦، ١١:٣٠:١٠ ص"},{"item_name":"24k/E","buy_price":"8037.26","sell_price":"7922.35","last_update":"١٧‏/٤‏/٢٠٢٦، ١١:٣٠:١٠ ص"},{"item_name":"5G/24K E","buy_price":"40495.0","sell_price":"39730.0","last_update":"١٧‏/٤‏/٢٠٢٦، ١١:٣٠:١٠ ص"},{"item_name":"10G/24K E","buy_price":"80989.0","sell_price":"79460.0","last_update":"١٧‏/٤‏/٢٠٢٦، ١١:٣٠:١٠ ص"},{"item_name":"20G/24K E","buy_price":"161899.0","sell_price":"158920.0","last_update":"١٧‏/٤‏/٢٠٢٦، ١١:٣٠:١٠ ص"},{"item_name":"1Ounce/24K E","buy_price":"251715.0","sell_price":"247145.0","last_update":"١٧‏/٤‏/٢٠٢٦، ١١:٣٠:١٠ ص"},{"item_name":"50G/24K E","buy_price":"404172.0","sell_price":"396876.0","last_update":"١٧‏/٤‏/٢٠٢٦، ١١:٣٠:١٠ ص"},{"item_name":"100G/24K E","buy_price":"808345.0","sell_price":"793752.0","last_update":"١٧‏/٤‏/٢٠٢٦، ١١:٣٠:١٠ ص"}]