[{"item_name":"1 Gold PoundE","buy_price":"54681.0","sell_price":"53643.0","last_update":"١١‏/٢‏/٢٠٢٦، ٦:٤٨:٥١ ص"},{"item_name":"21K/E","buy_price":"6786.6","sell_price":"6685.9","last_update":"١١‏/٢‏/٢٠٢٦، ٦:٤٨:٥١ ص"},{"item_name":"24k/E","buy_price":"7755.18","sell_price":"7640.07","last_update":"١١‏/٢‏/٢٠٢٦، ٦:٤٨:٥١ ص"},{"item_name":"5G/24K E","buy_price":"39084.0","sell_price":"38318.0","last_update":"١١‏/٢‏/٢٠٢٦، ٦:٤٨:٥١ ص"},{"item_name":"10G/24K E","buy_price":"78168.0","sell_price":"76637.0","last_update":"١١‏/٢‏/٢٠٢٦، ٦:٤٨:٥١ ص"},{"item_name":"20G/24K E","buy_price":"156256.0","sell_price":"153274.0","last_update":"١١‏/٢‏/٢٠٢٦، ٦:٤٨:٥١ ص"},{"item_name":"1Ounce/24K E","buy_price":"242940.0","sell_price":"238363.0","last_update":"١١‏/٢‏/٢٠٢٦، ٦:٤٨:٥١ ص"},{"item_name":"50G/24K E","buy_price":"390066.0","sell_price":"382759.0","last_update":"١١‏/٢‏/٢٠٢٦، ٦:٤٨:٥١ ص"},{"item_name":"100G/24K E","buy_price":"780131.0","sell_price":"765518.0","last_update":"١١‏/٢‏/٢٠٢٦، ٦:٤٨:٥١ ص"}]