[{"item_name":"1 Gold PoundE","buy_price":"60160.0","sell_price":"59119.0","last_update":"١٢‏/٣‏/٢٠٢٦، ٦:٥٧:١٩ م"},{"item_name":"21K/E","buy_price":"7471.6","sell_price":"7370.4","last_update":"١٢‏/٣‏/٢٠٢٦، ٦:٥٧:١٩ م"},{"item_name":"24k/E","buy_price":"8537.88","sell_price":"8422.26","last_update":"١٢‏/٣‏/٢٠٢٦، ٦:٥٧:١٩ م"},{"item_name":"5G/24K E","buy_price":"42998.0","sell_price":"42230.0","last_update":"١٢‏/٣‏/٢٠٢٦، ٦:٥٧:١٩ م"},{"item_name":"10G/24K E","buy_price":"85997.0","sell_price":"84460.0","last_update":"١٢‏/٣‏/٢٠٢٦، ٦:٥٧:١٩ م"},{"item_name":"20G/24K E","buy_price":"171914.0","sell_price":"168921.0","last_update":"١٢‏/٣‏/٢٠٢٦، ٦:٥٧:١٩ م"},{"item_name":"1Ounce/24K E","buy_price":"267289.0","sell_price":"262697.0","last_update":"١٢‏/٣‏/٢٠٢٦، ٦:٥٧:١٩ م"},{"item_name":"50G/24K E","buy_price":"429209.0","sell_price":"421876.0","last_update":"١٢‏/٣‏/٢٠٢٦، ٦:٥٧:١٩ م"},{"item_name":"100G/24K E","buy_price":"858418.0","sell_price":"843753.0","last_update":"١٢‏/٣‏/٢٠٢٦، ٦:٥٧:١٩ م"}]