[{"item_name":"1 Gold PoundE","buy_price":"57477.0","sell_price":"56434.0","last_update":"٣٠‏/٣‏/٢٠٢٦، ١:٥١:١٩ م"},{"item_name":"21K/E","buy_price":"7136.2","sell_price":"7034.8","last_update":"٣٠‏/٣‏/٢٠٢٦، ١:٥١:١٩ م"},{"item_name":"24k/E","buy_price":"8154.64","sell_price":"8038.8","last_update":"٣٠‏/٣‏/٢٠٢٦، ١:٥١:١٩ م"},{"item_name":"5G/24K E","buy_price":"41082.0","sell_price":"40312.0","last_update":"٣٠‏/٣‏/٢٠٢٦، ١:٥١:١٩ م"},{"item_name":"10G/24K E","buy_price":"82165.0","sell_price":"80626.0","last_update":"٣٠‏/٣‏/٢٠٢٦، ١:٥١:١٩ م"},{"item_name":"20G/24K E","buy_price":"164247.0","sell_price":"161250.0","last_update":"٣٠‏/٣‏/٢٠٢٦، ١:٥١:١٩ م"},{"item_name":"1Ounce/24K E","buy_price":"255367.0","sell_price":"250768.0","last_update":"٣٠‏/٣‏/٢٠٢٦، ١:٥١:١٩ م"},{"item_name":"50G/24K E","buy_price":"410043.0","sell_price":"402700.0","last_update":"٣٠‏/٣‏/٢٠٢٦، ١:٥١:١٩ م"},{"item_name":"100G/24K E","buy_price":"820085.0","sell_price":"805399.0","last_update":"٣٠‏/٣‏/٢٠٢٦، ١:٥١:١٩ م"}]