[{"item_name":"1 Gold PoundE","buy_price":"57643.0","sell_price":"56604.0","last_update":"ў¶вАП/ў§вАП/ўҐў†ўҐў¶ЎМ ў¶:ў•ўІ:ўҐў° ўЕ"},{"item_name":"21K/E","buy_price":"7156.9","sell_price":"7056.0","last_update":"ў¶вАП/ў§вАП/ўҐў†ўҐў¶ЎМ ў¶:ў•ўІ:ўҐў° ўЕ"},{"item_name":"24k/E","buy_price":"8178.36","sell_price":"8063.02","last_update":"ў¶вАП/ў§вАП/ўҐў†ўҐў¶ЎМ ў¶:ў•ўІ:ўҐў° ўЕ"},{"item_name":"5G/24K E","buy_price":"41200.0","sell_price":"40434.0","last_update":"ў¶вАП/ў§вАП/ўҐў†ўҐў¶ЎМ ў¶:ў•ўІ:ўҐў° ўЕ"},{"item_name":"10G/24K E","buy_price":"82401.0","sell_price":"80867.0","last_update":"ў¶вАП/ў§вАП/ўҐў†ўҐў¶ЎМ ў¶:ў•ўІ:ўҐў° ўЕ"},{"item_name":"20G/24K E","buy_price":"164722.0","sell_price":"161734.0","last_update":"ў¶вАП/ў§вАП/ўҐў†ўҐў¶ЎМ ў¶:ў•ўІ:ўҐў° ўЕ"},{"item_name":"1Ounce/24K E","buy_price":"256105.0","sell_price":"251521.0","last_update":"ў¶вАП/ў§вАП/ўҐў†ўҐў¶ЎМ ў¶:ў•ўІ:ўҐў° ўЕ"},{"item_name":"50G/24K E","buy_price":"411229.0","sell_price":"403911.0","last_update":"ў¶вАП/ў§вАП/ўҐў†ўҐў¶ЎМ ў¶:ў•ўІ:ўҐў° ўЕ"},{"item_name":"100G/24K E","buy_price":"822458.0","sell_price":"807821.0","last_update":"ў¶вАП/ў§вАП/ўҐў†ўҐў¶ЎМ ў¶:ў•ўІ:ўҐў° ўЕ"}]