[{"id":"karat_0","karat_name":"عيار 24","final_sell_price":7280,"final_buy_price":7326,"match_status":"إجماع ثلاثي","debug_sell":"S1:7280 | S2:7280 | S3:7280","debug_buy":"B1:7326 | B2:7326 | B3:7326"},{"id":"karat_1","karat_name":"عيار 22","final_sell_price":6672,"final_buy_price":6715,"match_status":"مرجع الموقع الثاني","debug_sell":"S1:6673 | S2:6672 | S3:0","debug_buy":"B1:6716 | B2:6715 | B3:0"},{"id":"karat_2","karat_name":"عيار 21","final_sell_price":6370,"final_buy_price":6410,"match_status":"إجماع ثلاثي","debug_sell":"S1:6370 | S2:6370 | S3:6370","debug_buy":"B1:6410 | B2:6410 | B3:6410"},{"id":"karat_3","karat_name":"عيار 18","final_sell_price":5460,"final_buy_price":5494,"match_status":"إجماع ثنائي (1 و 3)","debug_sell":"S1:5460 | S2:5458 | S3:5460","debug_buy":"B1:5494 | B2:5494 | B3:5494"},{"id":"karat_4","karat_name":"عيار 14","final_sell_price":4243,"final_buy_price":4273,"match_status":"مرجع الموقع الثاني","debug_sell":"S1:3640 | S2:4243 | S3:4246","debug_buy":"B1:3663 | B2:4273 | B3:4273"},{"id":"gold_coin","karat_name":"الجنيه الذهب","final_sell_price":50960,"final_buy_price":51280,"match_status":"إجماع ثنائي (1 و 2)","debug_sell":"S1:50960 | S2:50960 | S3:51282","debug_buy":"B1:51280 | B2:51280 | B3:51282"}]