[{"item_name":"1 Gold PoundE","buy_price":"59335.0","sell_price":"58292.0","last_update":"١٦‏/٣‏/٢٠٢٦، ٦:٣٦:١٩ م"},{"item_name":"21K/E","buy_price":"7368.4","sell_price":"7267.0","last_update":"١٦‏/٣‏/٢٠٢٦، ٦:٣٦:١٩ م"},{"item_name":"24k/E","buy_price":"8419.98","sell_price":"8304.13","last_update":"١٦‏/٣‏/٢٠٢٦، ٦:٣٦:١٩ م"},{"item_name":"5G/24K E","buy_price":"42409.0","sell_price":"41639.0","last_update":"١٦‏/٣‏/٢٠٢٦، ٦:٣٦:١٩ م"},{"item_name":"10G/24K E","buy_price":"84817.0","sell_price":"83279.0","last_update":"١٦‏/٣‏/٢٠٢٦، ٦:٣٦:١٩ م"},{"item_name":"20G/24K E","buy_price":"169555.0","sell_price":"166557.0","last_update":"١٦‏/٣‏/٢٠٢٦، ٦:٣٦:١٩ م"},{"item_name":"1Ounce/24K E","buy_price":"263621.0","sell_price":"259022.0","last_update":"١٦‏/٣‏/٢٠٢٦، ٦:٣٦:١٩ م"},{"item_name":"50G/24K E","buy_price":"423312.0","sell_price":"415969.0","last_update":"١٦‏/٣‏/٢٠٢٦، ٦:٣٦:١٩ م"},{"item_name":"100G/24K E","buy_price":"846625.0","sell_price":"831937.0","last_update":"١٦‏/٣‏/٢٠٢٦، ٦:٣٦:١٩ م"}]