[{"item_name":"1 Gold PoundE","buy_price":"53663.0","sell_price":"52786.0","last_update":"١٦‏/٢‏/٢٠٢٦، ١٢:٣٠:٥١ م"},{"item_name":"21K/E","buy_price":"6659.4","sell_price":"6578.8","last_update":"١٦‏/٢‏/٢٠٢٦، ١٢:٣٠:٥١ م"},{"item_name":"24k/E","buy_price":"7609.86","sell_price":"7517.73","last_update":"١٦‏/٢‏/٢٠٢٦، ١٢:٣٠:٥١ م"},{"item_name":"5G/24K E","buy_price":"38357.0","sell_price":"37707.0","last_update":"١٦‏/٢‏/٢٠٢٦، ١٢:٣٠:٥١ م"},{"item_name":"10G/24K E","buy_price":"76715.0","sell_price":"75413.0","last_update":"١٦‏/٢‏/٢٠٢٦، ١٢:٣٠:٥١ م"},{"item_name":"20G/24K E","buy_price":"153349.0","sell_price":"150826.0","last_update":"١٦‏/٢‏/٢٠٢٦، ١٢:٣٠:٥١ م"},{"item_name":"1Ounce/24K E","buy_price":"238419.0","sell_price":"234557.0","last_update":"١٦‏/٢‏/٢٠٢٦، ١٢:٣٠:٥١ م"},{"item_name":"50G/24K E","buy_price":"382798.0","sell_price":"376640.0","last_update":"١٦‏/٢‏/٢٠٢٦، ١٢:٣٠:٥١ م"},{"item_name":"100G/24K E","buy_price":"765596.0","sell_price":"753281.0","last_update":"١٦‏/٢‏/٢٠٢٦، ١٢:٣٠:٥١ م"}]