[{"item_name":"1 Gold PoundE","buy_price":"57446.0","sell_price":"56403.0","last_update":"١٦‏/٤‏/٢٠٢٦، ١٠:٥٤:٠٩ ص"},{"item_name":"21K/E","buy_price":"7132.2","sell_price":"7030.8","last_update":"١٦‏/٤‏/٢٠٢٦، ١٠:٥٤:٠٩ ص"},{"item_name":"24k/E","buy_price":"8150.17","sell_price":"8034.25","last_update":"١٦‏/٤‏/٢٠٢٦، ١٠:٥٤:٠٩ ص"},{"item_name":"5G/24K E","buy_price":"41059.0","sell_price":"40290.0","last_update":"١٦‏/٤‏/٢٠٢٦، ١٠:٥٤:٠٩ ص"},{"item_name":"10G/24K E","buy_price":"82119.0","sell_price":"80579.0","last_update":"١٦‏/٤‏/٢٠٢٦، ١٠:٥٤:٠٩ ص"},{"item_name":"20G/24K E","buy_price":"164158.0","sell_price":"161159.0","last_update":"١٦‏/٤‏/٢٠٢٦، ١٠:٥٤:٠٩ ص"},{"item_name":"1Ounce/24K E","buy_price":"255227.0","sell_price":"250626.0","last_update":"١٦‏/٤‏/٢٠٢٦، ١٠:٥٤:٠٩ ص"},{"item_name":"50G/24K E","buy_price":"409819.0","sell_price":"402472.0","last_update":"١٦‏/٤‏/٢٠٢٦، ١٠:٥٤:٠٩ ص"},{"item_name":"100G/24K E","buy_price":"819638.0","sell_price":"804944.0","last_update":"١٦‏/٤‏/٢٠٢٦، ١٠:٥٤:٠٩ ص"}]