[{"item_name":"1 Gold PoundE","buy_price":"58291.0","sell_price":"57248.0","last_update":"٩‏/٤‏/٢٠٢٦، ٦:٥١:٥٦ م"},{"item_name":"21K/E","buy_price":"7237.9","sell_price":"7136.5","last_update":"٩‏/٤‏/٢٠٢٦، ٦:٥١:٥٦ م"},{"item_name":"24k/E","buy_price":"8270.86","sell_price":"8154.99","last_update":"٩‏/٤‏/٢٠٢٦، ٦:٥١:٥٦ م"},{"item_name":"5G/24K E","buy_price":"41663.0","sell_price":"40894.0","last_update":"٩‏/٤‏/٢٠٢٦، ٦:٥١:٥٦ م"},{"item_name":"10G/24K E","buy_price":"83326.0","sell_price":"81787.0","last_update":"٩‏/٤‏/٢٠٢٦، ٦:٥١:٥٦ م"},{"item_name":"20G/24K E","buy_price":"166572.0","sell_price":"163574.0","last_update":"٩‏/٤‏/٢٠٢٦، ٦:٥١:٥٦ م"},{"item_name":"1Ounce/24K E","buy_price":"258982.0","sell_price":"254382.0","last_update":"٩‏/٤‏/٢٠٢٦، ٦:٥١:٥٦ م"},{"item_name":"50G/24K E","buy_price":"415855.0","sell_price":"408510.0","last_update":"٩‏/٤‏/٢٠٢٦، ٦:٥١:٥٦ م"},{"item_name":"100G/24K E","buy_price":"831710.0","sell_price":"817021.0","last_update":"٩‏/٤‏/٢٠٢٦، ٦:٥١:٥٦ م"}]