[{"item_name":"1 Gold PoundE","buy_price":"53559.0","sell_price":"52682.0","last_update":"١٨‏/٢‏/٢٠٢٦، ٦:٢١:٥١ م"},{"item_name":"21K/E","buy_price":"6646.3","sell_price":"6565.8","last_update":"١٨‏/٢‏/٢٠٢٦، ٦:٢١:٥١ م"},{"item_name":"24k/E","buy_price":"7594.91","sell_price":"7502.86","last_update":"١٨‏/٢‏/٢٠٢٦، ٦:٢١:٥١ م"},{"item_name":"5G/24K E","buy_price":"38283.0","sell_price":"37632.0","last_update":"١٨‏/٢‏/٢٠٢٦، ٦:٢١:٥١ م"},{"item_name":"10G/24K E","buy_price":"76565.0","sell_price":"75264.0","last_update":"١٨‏/٢‏/٢٠٢٦، ٦:٢١:٥١ م"},{"item_name":"20G/24K E","buy_price":"153050.0","sell_price":"150529.0","last_update":"١٨‏/٢‏/٢٠٢٦، ٦:٢١:٥١ م"},{"item_name":"1Ounce/24K E","buy_price":"237954.0","sell_price":"234095.0","last_update":"١٨‏/٢‏/٢٠٢٦، ٦:٢١:٥١ م"},{"item_name":"50G/24K E","buy_price":"382050.0","sell_price":"375897.0","last_update":"١٨‏/٢‏/٢٠٢٦، ٦:٢١:٥١ م"},{"item_name":"100G/24K E","buy_price":"764100.0","sell_price":"751794.0","last_update":"١٨‏/٢‏/٢٠٢٦، ٦:٢١:٥١ م"}]