[{"id":"karat_0","karat_name":"عيار 24","final_sell_price":6646,"final_buy_price":6680,"match_status":"إجماع ثنائي (1 و 3)","debug_sell":"S1:6646 | S2:6652 | S3:6646","debug_buy":"B1:6680 | B2:6686 | B3:6680"},{"id":"karat_1","karat_name":"عيار 22","final_sell_price":6098,"final_buy_price":6129,"match_status":"مرجع الموقع الثاني","debug_sell":"S1:6092 | S2:6098 | S3:0","debug_buy":"B1:6123 | B2:6129 | B3:0"},{"id":"karat_2","karat_name":"عيار 21","final_sell_price":5815,"final_buy_price":5845,"match_status":"إجماع ثنائي (1 و 3)","debug_sell":"S1:5815 | S2:5820 | S3:5815","debug_buy":"B1:5845 | B2:5850 | B3:5845"},{"id":"karat_3","karat_name":"عيار 18","final_sell_price":4984,"final_buy_price":5010,"match_status":"إجماع ثنائي (1 و 3)","debug_sell":"S1:4984 | S2:4988 | S3:4984","debug_buy":"B1:5010 | B2:5014 | B3:5010"},{"id":"karat_4","karat_name":"عيار 14","final_sell_price":3880,"final_buy_price":3900,"match_status":"مرجع الموقع الثاني","debug_sell":"S1:3323 | S2:3880 | S3:3876","debug_buy":"B1:3340 | B2:3900 | B3:3896"},{"id":"gold_coin","karat_name":"الجنيه الذهب","final_sell_price":46560,"final_buy_price":46760,"match_status":"مرجع الموقع الثاني","debug_sell":"S1:46520 | S2:46560 | S3:46760","debug_buy":"B1:46760 | B2:46800 | B3:46760"}]