[{"item_name":"1 Gold PoundE","buy_price":"57669.0","sell_price":"56627.0","last_update":"٧‏/٤‏/٢٠٢٦، ١١:٣٦:٣١ ص"},{"item_name":"21K/E","buy_price":"7160.2","sell_price":"7058.8","last_update":"٧‏/٤‏/٢٠٢٦، ١١:٣٦:٣١ ص"},{"item_name":"24k/E","buy_price":"8182.05","sell_price":"8066.29","last_update":"٧‏/٤‏/٢٠٢٦، ١١:٣٦:٣١ ص"},{"item_name":"5G/24K E","buy_price":"41219.0","sell_price":"40450.0","last_update":"٧‏/٤‏/٢٠٢٦، ١١:٣٦:٣١ ص"},{"item_name":"10G/24K E","buy_price":"82438.0","sell_price":"80900.0","last_update":"٧‏/٤‏/٢٠٢٦، ١١:٣٦:٣١ ص"},{"item_name":"20G/24K E","buy_price":"164795.0","sell_price":"161800.0","last_update":"٧‏/٤‏/٢٠٢٦، ١١:٣٦:٣١ ص"},{"item_name":"1Ounce/24K E","buy_price":"256219.0","sell_price":"251623.0","last_update":"٧‏/٤‏/٢٠٢٦، ١١:٣٦:٣١ ص"},{"item_name":"50G/24K E","buy_price":"411413.0","sell_price":"404074.0","last_update":"٧‏/٤‏/٢٠٢٦، ١١:٣٦:٣١ ص"},{"item_name":"100G/24K E","buy_price":"822827.0","sell_price":"808148.0","last_update":"٧‏/٤‏/٢٠٢٦، ١١:٣٦:٣١ ص"}]