[{"item_name":"1 Gold PoundE","buy_price":"57302.0","sell_price":"56262.0","last_update":"١٥‏/٤‏/٢٠٢٦، ٥:٠٣:٠٩ م"},{"item_name":"21K/E","buy_price":"7114.2","sell_price":"7013.3","last_update":"١٥‏/٤‏/٢٠٢٦، ٥:٠٣:٠٩ م"},{"item_name":"24k/E","buy_price":"8129.53","sell_price":"8014.21","last_update":"١٥‏/٤‏/٢٠٢٦، ٥:٠٣:٠٩ م"},{"item_name":"5G/24K E","buy_price":"40956.0","sell_price":"40189.0","last_update":"١٥‏/٤‏/٢٠٢٦، ٥:٠٣:٠٩ م"},{"item_name":"10G/24K E","buy_price":"81912.0","sell_price":"80379.0","last_update":"١٥‏/٤‏/٢٠٢٦، ٥:٠٣:٠٩ م"},{"item_name":"20G/24K E","buy_price":"163745.0","sell_price":"160758.0","last_update":"١٥‏/٤‏/٢٠٢٦، ٥:٠٣:٠٩ م"},{"item_name":"1Ounce/24K E","buy_price":"254585.0","sell_price":"250003.0","last_update":"١٥‏/٤‏/٢٠٢٦، ٥:٠٣:٠٩ م"},{"item_name":"50G/24K E","buy_price":"408787.0","sell_price":"401470.0","last_update":"١٥‏/٤‏/٢٠٢٦، ٥:٠٣:٠٩ م"},{"item_name":"100G/24K E","buy_price":"817574.0","sell_price":"802940.0","last_update":"١٥‏/٤‏/٢٠٢٦، ٥:٠٣:٠٩ م"}]