[{"item_name":"1 Gold PoundE","buy_price":"55054.0","sell_price":"54014.0","last_update":"٢٦‏/٣‏/٢٠٢٦، ١:٥٤:١٩ م"},{"item_name":"21K/E","buy_price":"6833.2","sell_price":"6732.2","last_update":"٢٦‏/٣‏/٢٠٢٦، ١:٥٤:١٩ م"},{"item_name":"24k/E","buy_price":"7808.46","sell_price":"7693.03","last_update":"٢٦‏/٣‏/٢٠٢٦، ١:٥٤:١٩ م"},{"item_name":"5G/24K E","buy_price":"39350.0","sell_price":"38583.0","last_update":"٢٦‏/٣‏/٢٠٢٦، ١:٥٤:١٩ م"},{"item_name":"10G/24K E","buy_price":"78701.0","sell_price":"77166.0","last_update":"٢٦‏/٣‏/٢٠٢٦، ١:٥٤:١٩ م"},{"item_name":"20G/24K E","buy_price":"157322.0","sell_price":"154333.0","last_update":"٢٦‏/٣‏/٢٠٢٦، ١:٥٤:١٩ م"},{"item_name":"1Ounce/24K E","buy_price":"244597.0","sell_price":"240011.0","last_update":"٢٦‏/٣‏/٢٠٢٦، ١:٥٤:١٩ م"},{"item_name":"50G/24K E","buy_price":"392730.0","sell_price":"385407.0","last_update":"٢٦‏/٣‏/٢٠٢٦، ١:٥٤:١٩ م"},{"item_name":"100G/24K E","buy_price":"785460.0","sell_price":"770815.0","last_update":"٢٦‏/٣‏/٢٠٢٦، ١:٥٤:١٩ م"}]