[{"item_name":"1 Gold PoundE","buy_price":"56286.0","sell_price":"55257.0","last_update":"٢٠‏/٤‏/٢٠٢٦، ٨:٠٩:٠٩ ص"},{"item_name":"21K/E","buy_price":"6987.2","sell_price":"6887.6","last_update":"٢٠‏/٤‏/٢٠٢٦، ٨:٠٩:٠٩ ص"},{"item_name":"24k/E","buy_price":"7984.42","sell_price":"7870.6","last_update":"٢٠‏/٤‏/٢٠٢٦، ٨:٠٩:٠٩ ص"},{"item_name":"5G/24K E","buy_price":"40230.0","sell_price":"39471.0","last_update":"٢٠‏/٤‏/٢٠٢٦، ٨:٠٩:٠٩ ص"},{"item_name":"10G/24K E","buy_price":"80461.0","sell_price":"78943.0","last_update":"٢٠‏/٤‏/٢٠٢٦، ٨:٠٩:٠٩ ص"},{"item_name":"20G/24K E","buy_price":"160842.0","sell_price":"157885.0","last_update":"٢٠‏/٤‏/٢٠٢٦، ٨:٠٩:٠٩ ص"},{"item_name":"1Ounce/24K E","buy_price":"250071.0","sell_price":"245535.0","last_update":"٢٠‏/٤‏/٢٠٢٦، ٨:٠٩:٠٩ ص"},{"item_name":"50G/24K E","buy_price":"401530.0","sell_price":"394288.0","last_update":"٢٠‏/٤‏/٢٠٢٦، ٨:٠٩:٠٩ ص"},{"item_name":"100G/24K E","buy_price":"803060.0","sell_price":"788576.0","last_update":"٢٠‏/٤‏/٢٠٢٦، ٨:٠٩:٠٩ ص"}]