[{"item_name":"1 Gold PoundE","buy_price":"55955.0","sell_price":"54909.0","last_update":"٢٥‏/٣‏/٢٠٢٦، ١٢:٣٦:١٩ م"},{"item_name":"21K/E","buy_price":"6945.9","sell_price":"6844.1","last_update":"٢٥‏/٣‏/٢٠٢٦، ١٢:٣٦:١٩ م"},{"item_name":"24k/E","buy_price":"7937.19","sell_price":"7820.9","last_update":"٢٥‏/٣‏/٢٠٢٦، ١٢:٣٦:١٩ م"},{"item_name":"5G/24K E","buy_price":"39994.0","sell_price":"39223.0","last_update":"٢٥‏/٣‏/٢٠٢٦، ١٢:٣٦:١٩ م"},{"item_name":"10G/24K E","buy_price":"79989.0","sell_price":"78445.0","last_update":"٢٥‏/٣‏/٢٠٢٦، ١٢:٣٦:١٩ م"},{"item_name":"20G/24K E","buy_price":"159897.0","sell_price":"156891.0","last_update":"٢٥‏/٣‏/٢٠٢٦، ١٢:٣٦:١٩ م"},{"item_name":"1Ounce/24K E","buy_price":"248602.0","sell_price":"243989.0","last_update":"٢٥‏/٣‏/٢٠٢٦، ١٢:٣٦:١٩ م"},{"item_name":"50G/24K E","buy_price":"399168.0","sell_price":"391802.0","last_update":"٢٥‏/٣‏/٢٠٢٦، ١٢:٣٦:١٩ م"},{"item_name":"100G/24K E","buy_price":"798336.0","sell_price":"783604.0","last_update":"٢٥‏/٣‏/٢٠٢٦، ١٢:٣٦:١٩ م"}]