[{"id":"karat_0","karat_name":"عيار 24","final_sell_price":7668,"final_buy_price":7714,"match_status":"إجماع ثلاثي","debug_sell":"S1:7668 | S2:7668 | S3:7668","debug_buy":"B1:7714 | B2:7714 | B3:7714"},{"id":"karat_1","karat_name":"عيار 22","final_sell_price":7028,"final_buy_price":7071,"match_status":"مرجع الموقع الثاني","debug_sell":"S1:7029 | S2:7028 | S3:0","debug_buy":"B1:7071 | B2:7071 | B3:0"},{"id":"karat_2","karat_name":"عيار 21","final_sell_price":6710,"final_buy_price":6750,"match_status":"إجماع ثنائي (1 و 2)","debug_sell":"S1:6710 | S2:6710 | S3:6709","debug_buy":"B1:6750 | B2:6750 | B3:6749"},{"id":"karat_3","karat_name":"عيار 18","final_sell_price":5751,"final_buy_price":5786,"match_status":"إجماع ثنائي (1 و 3)","debug_sell":"S1:5751 | S2:5750 | S3:5751","debug_buy":"B1:5786 | B2:5786 | B3:5785"},{"id":"karat_4","karat_name":"عيار 14","final_sell_price":4470,"final_buy_price":4500,"match_status":"مرجع الموقع الثاني","debug_sell":"S1:3834 | S2:4470 | S3:4473","debug_buy":"B1:3857 | B2:4500 | B3:4499"},{"id":"gold_coin","karat_name":"الجنيه الذهب","final_sell_price":53680,"final_buy_price":54000,"match_status":"إجماع ثنائي (1 و 2)","debug_sell":"S1:53680 | S2:53680 | S3:53998","debug_buy":"B1:54000 | B2:54000 | B3:53998"}]