[{"item_name":"1 Gold PoundE","buy_price":"57904.0","sell_price":"56862.0","last_update":"٥‏/٣‏/٢٠٢٦، ٦:٥٧:١٩ م"},{"item_name":"21K/E","buy_price":"7189.4","sell_price":"7088.2","last_update":"٥‏/٣‏/٢٠٢٦، ٦:٥٧:١٩ م"},{"item_name":"24k/E","buy_price":"8215.52","sell_price":"8099.81","last_update":"٥‏/٣‏/٢٠٢٦، ٦:٥٧:١٩ م"},{"item_name":"5G/24K E","buy_price":"41386.0","sell_price":"40618.0","last_update":"٥‏/٣‏/٢٠٢٦، ٦:٥٧:١٩ م"},{"item_name":"10G/24K E","buy_price":"82772.0","sell_price":"81235.0","last_update":"٥‏/٣‏/٢٠٢٦، ٦:٥٧:١٩ م"},{"item_name":"20G/24K E","buy_price":"165465.0","sell_price":"162470.0","last_update":"٥‏/٣‏/٢٠٢٦، ٦:٥٧:١٩ م"},{"item_name":"1Ounce/24K E","buy_price":"257260.0","sell_price":"252666.0","last_update":"٥‏/٣‏/٢٠٢٦، ٦:٥٧:١٩ م"},{"item_name":"50G/24K E","buy_price":"413087.0","sell_price":"405751.0","last_update":"٥‏/٣‏/٢٠٢٦، ٦:٥٧:١٩ م"},{"item_name":"100G/24K E","buy_price":"826174.0","sell_price":"811502.0","last_update":"٥‏/٣‏/٢٠٢٦، ٦:٥٧:١٩ م"}]