[{"item_name":"1 Gold PoundE","buy_price":"53389.0","sell_price":"52512.0","last_update":"١٨‏/٢‏/٢٠٢٦، ٨:٢١:٥١ م"},{"item_name":"21K/E","buy_price":"6625.1","sell_price":"6544.6","last_update":"١٨‏/٢‏/٢٠٢٦، ٨:٢١:٥١ م"},{"item_name":"24k/E","buy_price":"7570.6","sell_price":"7478.58","last_update":"١٨‏/٢‏/٢٠٢٦، ٨:٢١:٥١ م"},{"item_name":"5G/24K E","buy_price":"38161.0","sell_price":"37511.0","last_update":"١٨‏/٢‏/٢٠٢٦، ٨:٢١:٥١ م"},{"item_name":"10G/24K E","buy_price":"76322.0","sell_price":"75022.0","last_update":"١٨‏/٢‏/٢٠٢٦، ٨:٢١:٥١ م"},{"item_name":"20G/24K E","buy_price":"152564.0","sell_price":"150043.0","last_update":"١٨‏/٢‏/٢٠٢٦، ٨:٢١:٥١ م"},{"item_name":"1Ounce/24K E","buy_price":"237197.0","sell_price":"233340.0","last_update":"١٨‏/٢‏/٢٠٢٦، ٨:٢١:٥١ م"},{"item_name":"50G/24K E","buy_price":"380835.0","sell_price":"374683.0","last_update":"١٨‏/٢‏/٢٠٢٦، ٨:٢١:٥١ م"},{"item_name":"100G/24K E","buy_price":"761669.0","sell_price":"749365.0","last_update":"١٨‏/٢‏/٢٠٢٦، ٨:٢١:٥١ م"}]