[{"item_name":"1 Gold PoundE","buy_price":"54863.0","sell_price":"53981.0","last_update":"٢٠‏/٢‏/٢٠٢٦، ٢:٠٠:٥١ م"},{"item_name":"21K/E","buy_price":"6809.4","sell_price":"6728.1","last_update":"٢٠‏/٢‏/٢٠٢٦، ٢:٠٠:٥١ م"},{"item_name":"24k/E","buy_price":"7781.21","sell_price":"7688.33","last_update":"٢٠‏/٢‏/٢٠٢٦، ٢:٠٠:٥١ م"},{"item_name":"5G/24K E","buy_price":"39214.0","sell_price":"38560.0","last_update":"٢٠‏/٢‏/٢٠٢٦، ٢:٠٠:٥١ م"},{"item_name":"10G/24K E","buy_price":"78428.0","sell_price":"77119.0","last_update":"٢٠‏/٢‏/٢٠٢٦، ٢:٠٠:٥١ م"},{"item_name":"20G/24K E","buy_price":"156777.0","sell_price":"154239.0","last_update":"٢٠‏/٢‏/٢٠٢٦، ٢:٠٠:٥١ م"},{"item_name":"1Ounce/24K E","buy_price":"243749.0","sell_price":"239865.0","last_update":"٢٠‏/٢‏/٢٠٢٦، ٢:٠٠:٥١ م"},{"item_name":"50G/24K E","buy_price":"391367.0","sell_price":"385172.0","last_update":"٢٠‏/٢‏/٢٠٢٦، ٢:٠٠:٥١ م"},{"item_name":"100G/24K E","buy_price":"782735.0","sell_price":"770345.0","last_update":"٢٠‏/٢‏/٢٠٢٦، ٢:٠٠:٥١ م"}]