[{"item_name":"1 Gold PoundE","buy_price":"57703.0","sell_price":"56101.0","last_update":"٢٠‏/٣‏/٢٠٢٦، ٦:٤٨:١٩ ص"},{"item_name":"21K/E","buy_price":"7164.4","sell_price":"6993.1","last_update":"٢٠‏/٣‏/٢٠٢٦، ٦:٤٨:١٩ ص"},{"item_name":"24k/E","buy_price":"8186.94","sell_price":"7991.19","last_update":"٢٠‏/٣‏/٢٠٢٦، ٦:٤٨:١٩ ص"},{"item_name":"5G/24K E","buy_price":"41243.0","sell_price":"40074.0","last_update":"٢٠‏/٣‏/٢٠٢٦، ٦:٤٨:١٩ ص"},{"item_name":"10G/24K E","buy_price":"82487.0","sell_price":"80149.0","last_update":"٢٠‏/٣‏/٢٠٢٦، ٦:٤٨:١٩ ص"},{"item_name":"20G/24K E","buy_price":"164893.0","sell_price":"160297.0","last_update":"٢٠‏/٣‏/٢٠٢٦، ٦:٤٨:١٩ ص"},{"item_name":"1Ounce/24K E","buy_price":"256371.0","sell_price":"249287.0","last_update":"٢٠‏/٣‏/٢٠٢٦، ٦:٤٨:١٩ ص"},{"item_name":"50G/24K E","buy_price":"411658.0","sell_price":"400319.0","last_update":"٢٠‏/٣‏/٢٠٢٦، ٦:٤٨:١٩ ص"},{"item_name":"100G/24K E","buy_price":"823316.0","sell_price":"800637.0","last_update":"٢٠‏/٣‏/٢٠٢٦، ٦:٤٨:١٩ ص"}]