[{"item_name":"1 Gold PoundE","buy_price":"54654.0","sell_price":"53771.0","last_update":"٢٠‏/٢‏/٢٠٢٦، ٣:٢٤:٥١ م"},{"item_name":"21K/E","buy_price":"6783.2","sell_price":"6701.9","last_update":"٢٠‏/٢‏/٢٠٢٦، ٣:٢٤:٥١ م"},{"item_name":"24k/E","buy_price":"7751.29","sell_price":"7658.42","last_update":"٢٠‏/٢‏/٢٠٢٦، ٣:٢٤:٥١ م"},{"item_name":"5G/24K E","buy_price":"39065.0","sell_price":"38410.0","last_update":"٢٠‏/٢‏/٢٠٢٦، ٣:٢٤:٥١ م"},{"item_name":"10G/24K E","buy_price":"78129.0","sell_price":"76820.0","last_update":"٢٠‏/٢‏/٢٠٢٦، ٣:٢٤:٥١ م"},{"item_name":"20G/24K E","buy_price":"156178.0","sell_price":"153641.0","last_update":"٢٠‏/٢‏/٢٠٢٦، ٣:٢٤:٥١ م"},{"item_name":"1Ounce/24K E","buy_price":"242819.0","sell_price":"238934.0","last_update":"٢٠‏/٢‏/٢٠٢٦، ٣:٢٤:٥١ م"},{"item_name":"50G/24K E","buy_price":"389871.0","sell_price":"383676.0","last_update":"٢٠‏/٢‏/٢٠٢٦، ٣:٢٤:٥١ م"},{"item_name":"100G/24K E","buy_price":"779742.0","sell_price":"767353.0","last_update":"٢٠‏/٢‏/٢٠٢٦، ٣:٢٤:٥١ م"}]