[{"item_name":"1 Gold PoundE","buy_price":"56253.0","sell_price":"55223.0","last_update":"ЩўЩЈвҖҸ/ЩўвҖҸ/ЩўЩ ЩўЩҰШҢ ЩЎ:ЩЎЩЁ:ЩҘЩЎ Щ…"},{"item_name":"21K/E","buy_price":"6983.2","sell_price":"6883.4","last_update":"ЩўЩЈвҖҸ/ЩўвҖҸ/ЩўЩ ЩўЩҰШҢ ЩЎ:ЩЎЩЁ:ЩҘЩЎ Щ…"},{"item_name":"24k/E","buy_price":"7979.78","sell_price":"7865.78","last_update":"ЩўЩЈвҖҸ/ЩўвҖҸ/ЩўЩ ЩўЩҰШҢ ЩЎ:ЩЎЩЁ:ЩҘЩЎ Щ…"},{"item_name":"5G/24K E","buy_price":"40207.0","sell_price":"39447.0","last_update":"ЩўЩЈвҖҸ/ЩўвҖҸ/ЩўЩ ЩўЩҰШҢ ЩЎ:ЩЎЩЁ:ЩҘЩЎ Щ…"},{"item_name":"10G/24K E","buy_price":"80415.0","sell_price":"78894.0","last_update":"ЩўЩЈвҖҸ/ЩўвҖҸ/ЩўЩ ЩўЩҰШҢ ЩЎ:ЩЎЩЁ:ЩҘЩЎ Щ…"},{"item_name":"20G/24K E","buy_price":"160749.0","sell_price":"157789.0","last_update":"ЩўЩЈвҖҸ/ЩўвҖҸ/ЩўЩ ЩўЩҰШҢ ЩЎ:ЩЎЩЁ:ЩҘЩЎ Щ…"},{"item_name":"1Ounce/24K E","buy_price":"249927.0","sell_price":"245385.0","last_update":"ЩўЩЈвҖҸ/ЩўвҖҸ/ЩўЩ ЩўЩҰШҢ ЩЎ:ЩЎЩЁ:ЩҘЩЎ Щ…"},{"item_name":"50G/24K E","buy_price":"401298.0","sell_price":"394046.0","last_update":"ЩўЩЈвҖҸ/ЩўвҖҸ/ЩўЩ ЩўЩҰШҢ ЩЎ:ЩЎЩЁ:ЩҘЩЎ Щ…"},{"item_name":"100G/24K E","buy_price":"802595.0","sell_price":"788093.0","last_update":"ЩўЩЈвҖҸ/ЩўвҖҸ/ЩўЩ ЩўЩҰШҢ ЩЎ:ЩЎЩЁ:ЩҘЩЎ Щ…"}]