[{"item_name":"1 Gold PoundE","buy_price":"58120.0","sell_price":"57081.0","last_update":"١٠‏/٤‏/٢٠٢٦، ١٠:٥٤:٥٦ ص"},{"item_name":"21K/E","buy_price":"7216.5","sell_price":"7115.6","last_update":"١٠‏/٤‏/٢٠٢٦، ١٠:٥٤:٥٦ ص"},{"item_name":"24k/E","buy_price":"8246.43","sell_price":"8131.17","last_update":"١٠‏/٤‏/٢٠٢٦، ١٠:٥٤:٥٦ ص"},{"item_name":"5G/24K E","buy_price":"41540.0","sell_price":"40773.0","last_update":"١٠‏/٤‏/٢٠٢٦، ١٠:٥٤:٥٦ ص"},{"item_name":"10G/24K E","buy_price":"83080.0","sell_price":"81545.0","last_update":"١٠‏/٤‏/٢٠٢٦، ١٠:٥٤:٥٦ ص"},{"item_name":"20G/24K E","buy_price":"166080.0","sell_price":"163090.0","last_update":"١٠‏/٤‏/٢٠٢٦، ١٠:٥٤:٥٦ ص"},{"item_name":"1Ounce/24K E","buy_price":"258217.0","sell_price":"253630.0","last_update":"١٠‏/٤‏/٢٠٢٦، ١٠:٥٤:٥٦ ص"},{"item_name":"50G/24K E","buy_price":"414624.0","sell_price":"407300.0","last_update":"١٠‏/٤‏/٢٠٢٦، ١٠:٥٤:٥٦ ص"},{"item_name":"100G/24K E","buy_price":"829248.0","sell_price":"814601.0","last_update":"١٠‏/٤‏/٢٠٢٦، ١٠:٥٤:٥٦ ص"}]