[{"item_name":"1 Gold PoundE","buy_price":"57690.0","sell_price":"56648.0","last_update":"١٤‏/٤‏/٢٠٢٦، ١٢:٠٣:٠٩ م"},{"item_name":"21K/E","buy_price":"7162.7","sell_price":"7061.6","last_update":"١٤‏/٤‏/٢٠٢٦، ١٢:٠٣:٠٩ م"},{"item_name":"24k/E","buy_price":"8185.01","sell_price":"8069.37","last_update":"١٤‏/٤‏/٢٠٢٦، ١٢:٠٣:٠٩ م"},{"item_name":"5G/24K E","buy_price":"41234.0","sell_price":"40465.0","last_update":"١٤‏/٤‏/٢٠٢٦، ١٢:٠٣:٠٩ م"},{"item_name":"10G/24K E","buy_price":"82467.0","sell_price":"80931.0","last_update":"١٤‏/٤‏/٢٠٢٦، ١٢:٠٣:٠٩ م"},{"item_name":"20G/24K E","buy_price":"164854.0","sell_price":"161861.0","last_update":"١٤‏/٤‏/٢٠٢٦، ١٢:٠٣:٠٩ م"},{"item_name":"1Ounce/24K E","buy_price":"256311.0","sell_price":"251719.0","last_update":"١٤‏/٤‏/٢٠٢٦، ١٢:٠٣:٠٩ م"},{"item_name":"50G/24K E","buy_price":"411561.0","sell_price":"404229.0","last_update":"١٤‏/٤‏/٢٠٢٦، ١٢:٠٣:٠٩ م"},{"item_name":"100G/24K E","buy_price":"823123.0","sell_price":"808457.0","last_update":"١٤‏/٤‏/٢٠٢٦، ١٢:٠٣:٠٩ م"}]