[{"item_name":"1 Gold PoundE","buy_price":"58343.0","sell_price":"57296.0","last_update":"٦‏/٤‏/٢٠٢٦، ٨:٥٤:٢١ ص"},{"item_name":"21K/E","buy_price":"7244.4","sell_price":"7142.4","last_update":"٦‏/٤‏/٢٠٢٦، ٨:٥٤:٢١ ص"},{"item_name":"24k/E","buy_price":"8278.34","sell_price":"8161.8","last_update":"٦‏/٤‏/٢٠٢٦، ٨:٥٤:٢١ ص"},{"item_name":"5G/24K E","buy_price":"41700.0","sell_price":"40928.0","last_update":"٦‏/٤‏/٢٠٢٦، ٨:٥٤:٢١ ص"},{"item_name":"10G/24K E","buy_price":"83401.0","sell_price":"81855.0","last_update":"٦‏/٤‏/٢٠٢٦، ٨:٥٤:٢١ ص"},{"item_name":"20G/24K E","buy_price":"166722.0","sell_price":"163710.0","last_update":"٦‏/٤‏/٢٠٢٦، ٨:٥٤:٢١ ص"},{"item_name":"1Ounce/24K E","buy_price":"259215.0","sell_price":"254594.0","last_update":"٦‏/٤‏/٢٠٢٦، ٨:٥٤:٢١ ص"},{"item_name":"50G/24K E","buy_price":"416229.0","sell_price":"408851.0","last_update":"٦‏/٤‏/٢٠٢٦، ٨:٥٤:٢١ ص"},{"item_name":"100G/24K E","buy_price":"832458.0","sell_price":"817702.0","last_update":"٦‏/٤‏/٢٠٢٦، ٨:٥٤:٢١ ص"}]