[{"item_name":"1 Gold PoundE","buy_price":"58092.0","sell_price":"57053.0","last_update":"١٠‏/٤‏/٢٠٢٦، ١١:١٥:٥٦ ص"},{"item_name":"21K/E","buy_price":"7213.0","sell_price":"7112.1","last_update":"١٠‏/٤‏/٢٠٢٦، ١١:١٥:٥٦ ص"},{"item_name":"24k/E","buy_price":"8242.38","sell_price":"8127.18","last_update":"١٠‏/٤‏/٢٠٢٦، ١١:١٥:٥٦ ص"},{"item_name":"5G/24K E","buy_price":"41521.0","sell_price":"40754.0","last_update":"١٠‏/٤‏/٢٠٢٦، ١١:١٥:٥٦ ص"},{"item_name":"10G/24K E","buy_price":"83041.0","sell_price":"81509.0","last_update":"١٠‏/٤‏/٢٠٢٦، ١١:١٥:٥٦ ص"},{"item_name":"20G/24K E","buy_price":"166002.0","sell_price":"163018.0","last_update":"١٠‏/٤‏/٢٠٢٦، ١١:١٥:٥٦ ص"},{"item_name":"1Ounce/24K E","buy_price":"258096.0","sell_price":"253517.0","last_update":"١٠‏/٤‏/٢٠٢٦، ١١:١٥:٥٦ ص"},{"item_name":"50G/24K E","buy_price":"414431.0","sell_price":"407119.0","last_update":"١٠‏/٤‏/٢٠٢٦، ١١:١٥:٥٦ ص"},{"item_name":"100G/24K E","buy_price":"828862.0","sell_price":"814238.0","last_update":"١٠‏/٤‏/٢٠٢٦، ١١:١٥:٥٦ ص"}]