[{"item_name":"1 Gold PoundE","buy_price":"57304.0","sell_price":"56264.0","last_update":"١٥‏/٤‏/٢٠٢٦، ٣:٤٥:٠٩ م"},{"item_name":"21K/E","buy_price":"7114.4","sell_price":"7013.5","last_update":"١٥‏/٤‏/٢٠٢٦، ٣:٤٥:٠٩ م"},{"item_name":"24k/E","buy_price":"8129.81","sell_price":"8014.47","last_update":"١٥‏/٤‏/٢٠٢٦، ٣:٤٥:٠٩ م"},{"item_name":"5G/24K E","buy_price":"40958.0","sell_price":"40191.0","last_update":"١٥‏/٤‏/٢٠٢٦، ٣:٤٥:٠٩ م"},{"item_name":"10G/24K E","buy_price":"81915.0","sell_price":"80382.0","last_update":"١٥‏/٤‏/٢٠٢٦، ٣:٤٥:٠٩ م"},{"item_name":"20G/24K E","buy_price":"163750.0","sell_price":"160763.0","last_update":"١٥‏/٤‏/٢٠٢٦، ٣:٤٥:٠٩ م"},{"item_name":"1Ounce/24K E","buy_price":"254594.0","sell_price":"250011.0","last_update":"١٥‏/٤‏/٢٠٢٦، ٣:٤٥:٠٩ م"},{"item_name":"50G/24K E","buy_price":"408801.0","sell_price":"401483.0","last_update":"١٥‏/٤‏/٢٠٢٦، ٣:٤٥:٠٩ م"},{"item_name":"100G/24K E","buy_price":"817602.0","sell_price":"802966.0","last_update":"١٥‏/٤‏/٢٠٢٦، ٣:٤٥:٠٩ م"}]