[{"item_name":"1 Gold PoundE","buy_price":"54722.0","sell_price":"53668.0","last_update":"٩‏/٢‏/٢٠٢٦، ٨:٥٧:٥١ ص"},{"item_name":"21K/E","buy_price":"6791.8","sell_price":"6689.0","last_update":"٩‏/٢‏/٢٠٢٦، ٨:٥٧:٥١ ص"},{"item_name":"24k/E","buy_price":"7761.09","sell_price":"7643.63","last_update":"٩‏/٢‏/٢٠٢٦، ٨:٥٧:٥١ ص"},{"item_name":"5G/24K E","buy_price":"39114.0","sell_price":"38336.0","last_update":"٩‏/٢‏/٢٠٢٦، ٨:٥٧:٥١ ص"},{"item_name":"10G/24K E","buy_price":"78227.0","sell_price":"76672.0","last_update":"٩‏/٢‏/٢٠٢٦، ٨:٥٧:٥١ ص"},{"item_name":"20G/24K E","buy_price":"156374.0","sell_price":"153345.0","last_update":"٩‏/٢‏/٢٠٢٦، ٨:٥٧:٥١ ص"},{"item_name":"1Ounce/24K E","buy_price":"243123.0","sell_price":"238474.0","last_update":"٩‏/٢‏/٢٠٢٦، ٨:٥٧:٥١ ص"},{"item_name":"50G/24K E","buy_price":"390361.0","sell_price":"382937.0","last_update":"٩‏/٢‏/٢٠٢٦، ٨:٥٧:٥١ ص"},{"item_name":"100G/24K E","buy_price":"780722.0","sell_price":"765874.0","last_update":"٩‏/٢‏/٢٠٢٦، ٨:٥٧:٥١ ص"}]