[{"bank_name":"الأهلي المصري (NBE)","buy_price":"167.75","sell_price":"173.06","last_update":""},{"bank_name":"كريدي أجريكول (CA)","buy_price":"170.86","sell_price":"172.84","last_update":""},{"bank_name":"أبوظبي الإسلامي (ADIB)","buy_price":"169.84","sell_price":"174.96","last_update":""},{"bank_name":"الأهلي الكويتي (ABK)","buy_price":"167.75","sell_price":"173.22","last_update":""},{"bank_name":"المصرف العربي (AIB)","buy_price":"173.06","sell_price":"173.39","last_update":""},{"bank_name":"التجاري الدولي (CIB)","buy_price":"169.60","sell_price":"173.39","last_update":""},{"bank_name":"بنك نكست (NXT)","buy_price":"164.47","sell_price":"175.06","last_update":""},{"bank_name":"بنك مصر (BM)","buy_price":"167.59","sell_price":"172.37","last_update":""},{"bank_name":"بنك الإسكندرية (ALEXBANK)","buy_price":"166.27","sell_price":"172.45","last_update":""},{"bank_name":"المصري الخليجي (EG Bank)","buy_price":"163.52","sell_price":"172.57","last_update":""},{"bank_name":"الإمارات دبي (Emirates NBD)","buy_price":"165.95","sell_price":"173.88","last_update":""},{"bank_name":"تنمية الصادرات (EBank)","buy_price":"168.82","sell_price":"175.37","last_update":""},{"bank_name":"بنك فيصل (Faisal)","buy_price":"167.90","sell_price":"173.22","last_update":""},{"bank_name":"التعمير والإسكان (HDB)","buy_price":"166.75","sell_price":"174.04","last_update":""},{"bank_name":"التنمية الصناعية (IDB)","buy_price":"0.00","sell_price":"0.00","last_update":""},{"bank_name":"ميد بنك (MID Bank)","buy_price":"162.70","sell_price":"173.57","last_update":""},{"bank_name":"الكويت الوطني (NBK)","buy_price":"168.54","sell_price":"175.73","last_update":""},{"bank_name":"بنك الشركة المصرفية (SAIB)","buy_price":"173.05","sell_price":"173.44","last_update":""},{"bank_name":"قناة السويس (SCB)","buy_price":"171.33","sell_price":"173.33","last_update":""},{"bank_name":"المصرف المتحد (UB)","buy_price":"159.85","sell_price":"173.28","last_update":""},{"bank_name":"اتش اس بي سي (HSBC)","buy_price":"172.93","sell_price":"173.20","last_update":""},{"bank_name":"بنك بيت التمويل الكويتي (KFH)","buy_price":"167.84","sell_price":"175.13","last_update":""},{"bank_name":"العربي الأفريقي (AAIB)","buy_price":"169.83","sell_price":"173.57","last_update":""},{"bank_name":"أبوظبي اﻷول (FABMISR)","buy_price":"166.14","sell_price":"172.52","last_update":""}]